Chunk/CCcomm.py
Chunk/LRcomm.py
Chunk/__init__.py
Chunk/preprocess.py
Chunk/utils.py
Chunk/data/GeneLength.txt
Chunk/data/Human-2020-Cabello-Aguilar-LR-pairs.csv
chunk_py-1.0.6.dist-info/LICENSE.txt
chunk_py-1.0.6.dist-info/METADATA
chunk_py-1.0.6.dist-info/WHEEL
chunk_py-1.0.6.dist-info/top_level.txt
chunk_py-1.0.6.dist-info/RECORD
