Metadata-Version: 2.1
Name: chunk-py
Version: 1.0.6
Summary: TransCriptomics pHeotype Unity aNalysis Kit
Home-page: https://github.com/yyp1999/Chunk
Author: Youpeng Yang
Author-email: yypeng1999@gmail.com
Classifier: Development Status :: 5 - Production/Stable
Classifier: Intended Audience :: Science/Research
Classifier: License :: OSI Approved :: MIT License
Classifier: Programming Language :: Python :: 3
Classifier: Programming Language :: Python :: 3.8
Classifier: Programming Language :: Python :: 3.9
Classifier: Programming Language :: Python :: 3.10
Classifier: Programming Language :: Python :: 3.11
Classifier: Programming Language :: Python :: 3.12
Classifier: Operating System :: OS Independent
Requires-Python: >=3.8
License-File: LICENSE.txt
Requires-Dist: pandas
Requires-Dist: numpy
Requires-Dist: matplotlib
Requires-Dist: scikit-learn
Requires-Dist: scipy
Requires-Dist: seaborn
Requires-Dist: statsmodels
Requires-Dist: plotly
Requires-Dist: IPython
Requires-Dist: scanpy
Requires-Dist: qnorm
Requires-Dist: torch
Requires-Dist: numba
Requires-Dist: anndata
Requires-Dist: openchord
Requires-Dist: adjustText
Requires-Dist: PyComplexHeatmap
